setup.py
pypastebin/__main__.py
pypastebin/database.py
pypastebin/main.py
pypastebin/settings.py
pypastebin.egg-info/PKG-INFO
pypastebin.egg-info/SOURCES.txt
pypastebin.egg-info/dependency_links.txt
pypastebin.egg-info/top_level.txt
pypastebin/pages/api.py
pypastebin/pages/index.py
pypastebin/pages/view.py
pypastebin/static/__init__.py
pypastebin/static/index.html