Metadata-Version: 2.1
Name: pypastebin
Version: 0.0.2
Summary: python paste servivei
Home-page: https://gitlab.com/sulincix/sitemaker
Author: sulincix
Author-email: aa@aa.aa
